packaging_workshop_pmat/__init__.py
packaging_workshop_pmat/__main__.py
packaging_workshop_pmat/cli.py
packaging_workshop_pmat/quality_demo.py
packaging_workshop_pmat-0.1.0.dist-info/METADATA
packaging_workshop_pmat-0.1.0.dist-info/WHEEL
packaging_workshop_pmat-0.1.0.dist-info/entry_points.txt
packaging_workshop_pmat-0.1.0.dist-info/RECORD
