Metadata-Version: 2.4
Name: packaging_workshop_pmat
Version: 0.1.0
Summary: Workshop package for practicing modern Python packaging.
Requires-Python: >=3.13
Provides-Extra: dev
Requires-Dist: black; extra == 'dev'
Requires-Dist: mypy; extra == 'dev'
Requires-Dist: pytest; extra == 'dev'
Requires-Dist: ruff; extra == 'dev'
